{"stats":{"minecraft:broken":{"minecraft:golden_boots":1,"minecraft:iron_chestplate":1,"minecraft:shield":1,"minecraft:iron_axe":2},"minecraft:killed":{"darkestsouls:gravetender_hollow_longsword":1,"darkestsouls:bonewheel":4,"minecraft:witch":3,"darkestsouls:skeleton_curved_swords":6,"darkestsouls:ashen_blood_beast_patient":2,"spore:braiomil":3,"minecraft:spider":17,"darkestsouls:church_doctor_scythe":3,"mysticsbiomes:sea_otter":1,"darkestsouls:leech":3,"mysticsbiomes:rainbow_chicken":1,"mysticsbiomes:chocolate_cow":1,"darkestsouls:sewer_centipede":7,"minecraft:skeleton":16,"minecraft:chicken":4,"darkestsouls:beast_patient":21,"mysticsbiomes:vanilla_cow":1,"darkestsouls:church_doctor_lantern":4,"darkestsouls:hollow_assassin":9,"darkestsouls:hollow_longsword":3,"minecraft:pig":6,"spore:inf_player":7,"spore:inf_wanderer":4,"minecraft:zombie_villager":1,"minecraft:salmon":3,"spore:scamper":2,"spore:inf_drowned":1,"darkestsouls:gravetender_hollow_broken_straightsword":1,"minecraft:creeper":24,"minecraft:sheep":6,"spore:inf_villager":11,"darkestsouls:skeleton_spear":3,"minecraft:pillager":1,"spore:mound":5,"minecraft:zombie":21,"spore:inf_human":32,"spore:howler":2,"spore:knight":6,"minecraft:cow":14,"darkestsouls:hollow_axe":3,"spore:ogre":1,"minecraft:vindicator":2,"minecraft:slime":22,"spore:griefer":1,"darkestsouls:hollow_broken_straightsword":3,"darkestsouls:skeleton_falchion":11,"minecraft:drowned":1,"minecraft:rabbit":1,"minecraft:bat":1,"minecraft:polar_bear":1,"spore:inf_pillager":12,"spore:brot":1,"darkestsouls:cloaked_beast_patient":16,"spore:inf_witch":4,"spore:busser":2,"darkestsouls:skeleton_swordsman_twin_shotels":1,"spore:inf_husk":8,"spore:slasher":2,"minecraft:enderman":1},"minecraft:used":{"mysticsbiomes:stripped_cherry_log":1,"minecraft:chest":27,"minecraft:shield":94,"mysticsbiomes:pink_cherry_blossom_sapling":1,"minecraft:iron_chestplate":1,"minecraft:mutton":2,"minecraft:carrot":83,"minecraft:tuff":2,"jeg:grenade":3,"minecraft:mangrove_log":9,"minecraft:oak_sapling":11,"minecraft:furnace":9,"minecraft:damaged_anvil":3,"minecraft:spruce_door":4,"spore:armads":916,"minecraft:oak_planks":464,"minecraft:stone_pickaxe":24,"minecraft:mangrove_planks":40,"minecraft:wooden_pickaxe":11,"jeg:assault_rifle":329,"minecraft:white_wool":2,"minecraft:golden_apple":2,"minecraft:mushroom_stew":1,"minecraft:blast_furnace":1,"minecraft:mangrove_door":3,"minecraft:bread":9,"minecraft:enchanting_table":1,"spore:scythe":1,"minecraft:spruce_planks":1,"minecraft:wooden_shovel":43,"mysticsbiomes:cherry_log":1,"mysticsbiomes:cyan_egg":1,"minecraft:torch":139,"minecraft:dirt":68,"mysticsbiomes:cherry_planks":269,"minecraft:wooden_axe":38,"minecraft:iron_axe":409,"mysticsbiomes:cherry_stairs":16,"mysticsbiomes:spring_bamboo":215,"minecraft:golden_carrot":7,"minecraft:beef":4,"minecraft:cooked_beef":69,"minecraft:cobbled_deepslate":50,"minecraft:water_bucket":25,"jeg:combat_rifle":245,"minecraft:brown_mushroom":2,"minecraft:salmon":3,"minecraft:crafting_table":12,"minecraft:white_bed":5,"minecraft:smoker":1,"minecraft:diamond_pickaxe":167,"minecraft:apple":3,"minecraft:chicken":1,"minecraft:iron_pickaxe":680,"minecraft:suspicious_stew":1,"minecraft:lapis_ore":4,"jeg:scrap_workbench":3,"minecraft:stone_axe":94,"minecraft:cobblestone":118,"minecraft:potion":1,"minecraft:porkchop":3,"minecraft:cooked_porkchop":7,"minecraft:bucket":26},"minecraft:mined":{"minecraft:spruce_planks":2,"minecraft:white_bed":3,"minecraft:brewing_stand":1,"minecraft:obsidian":43,"minecraft:grass_block":8,"spore:fungal_stem":2,"darkestsouls:deepslate_siderite_ore":1,"minecraft:spawner":2,"minecraft:raw_iron_block":1,"mysticsbiomes:stripped_cherry_log":1,"minecraft:iron_ore":93,"minecraft:cobbled_deepslate":6,"minecraft:deepslate_lapis_ore":2,"spore:growth_mycelium":2,"mysticsbiomes:cherry_log":113,"minecraft:blackstone":8,"mysticsbiomes:sea_shrub_leaves":2,"spore:growths_big":4,"mysticsbiomes:spring_bamboo_sapling":2,"minecraft:torch":2,"minecraft:chest":12,"minecraft:sugar_cane":8,"minecraft:oak_planks":86,"minecraft:damaged_anvil":3,"minecraft:wall_torch":5,"minecraft:cherry_slab":1,"minecraft:deepslate_copper_ore":2,"minecraft:cherry_fence":2,"minecraft:lilac":3,"minecraft:stone_brick_stairs":1,"minecraft:grass":11,"minecraft:oak_log":135,"minecraft:dirt":3,"minecraft:mangrove_log":104,"minecraft:smooth_basalt":2,"darkestsouls:deepslate_cinnabar_ore":1,"minecraft:dispenser":3,"minecraft:deepslate":130,"spore:remains":12,"minecraft:tuff":19,"minecraft:deepslate_diamond_ore":29,"minecraft:stripped_mangrove_log":4,"mysticsbiomes:budding_peony_leaves":2,"spore:rotten_bush":1,"spore:growths_small":2,"minecraft:furnace":7,"minecraft:carrots":20,"mysticsbiomes:cherry_planks":45,"mysticsbiomes:cherry_door":2,"minecraft:deepslate_iron_ore":8,"minecraft:rail":3,"spore:biomass_bulb":2,"minecraft:stone":209,"minecraft:bone_block":11,"minecraft:white_wool":2,"minecraft:birch_pressure_plate":3,"minecraft:podzol":60,"minecraft:light_gray_carpet":1,"mysticsbiomes:spring_bamboo":65,"jeg:scrap_ore":36,"mysticsbiomes:peony_leaves":1,"minecraft:crafting_table":10,"minecraft:tall_grass":3,"minecraft:copper_ore":2,"minecraft:lapis_ore":20,"minecraft:deepslate_gold_ore":57,"jeg:deepslate_scrap_ore":9,"minecraft:birch_planks":4,"jeg:scrap_workbench":2,"spore:bloomfung2":1,"minecraft:spruce_log":8,"minecraft:mangrove_planks":1,"spore:fungal_stem_top":1,"minecraft:coal_ore":147,"darkestsouls:cinnabar_ore":1,"minecraft:small_dripleaf":2},"minecraft:dropped":{"minecraft:iron_sword":1,"minecraft:brown_mushroom":3,"minecraft:birch_planks":66,"minecraft:lapis_lazuli":32,"minecraft:cooked_beef":18,"minecraft:crafting_table":1,"minecraft:leather":1,"minecraft:flint":4,"mysticsbiomes:white_cherry_blossom_sapling":12,"minecraft:amethyst_shard":5,"minecraft:iron_pickaxe":1,"minecraft:gold_ingot":2,"darkestsouls:titanite_fragment":4,"minecraft:cobbled_deepslate":1,"minecraft:obsidian":6,"minecraft:birch_sapling":6,"minecraft:rotten_flesh":2,"minecraft:light_gray_carpet":1,"jeg:rifle_ammo":193,"darkestsouls:beast_blood_clump":1,"minecraft:white_bed":1,"minecraft:chest":1,"minecraft:arrow":4,"spore:armads":1,"minecraft:glass":1,"minecraft:iron_ingot":1,"minecraft:wheat_seeds":1,"minecraft:lilac":1,"minecraft:iron_helmet":2,"minecraft:golden_carrot":1,"minecraft:torch":30,"minecraft:wooden_axe":2,"minecraft:iron_leggings":1,"minecraft:raw_iron_block":1,"spore:mutated_heart":1,"minecraft:bowl":1,"minecraft:experience_bottle":13,"minecraft:birch_pressure_plate":1,"minecraft:iron_boots":1,"spore:scythe":1,"spore:mutated_fiber":1,"mysticsbiomes:pink_cherry_blossom_sapling":6,"minecraft:spruce_planks":1,"minecraft:iron_chestplate":2,"jeg:combat_rifle":1},"minecraft:picked_up":{"minecraft:wooden_axe":7,"minecraft:iron_chestplate":8,"spore:mutated_heart":30,"minecraft:potion":2,"minecraft:brewing_stand":2,"darkestsouls:beast_blood_clump":63,"minecraft:lapis_block":1,"minecraft:string":45,"minecraft:raw_copper":38,"minecraft:iron_leggings":3,"darkestsouls:rune_fragment":2,"minecraft:experience_bottle":26,"jeg:trumpet":1,"minecraft:cobbled_deepslate":116,"minecraft:spruce_planks":4,"minecraft:iron_pickaxe":9,"minecraft:furnace":7,"minecraft:mangrove_log":272,"minecraft:iron_boots":3,"minecraft:stick":212,"spore:plated_muscle":5,"jeg:pistol_ammo":128,"minecraft:torch":253,"minecraft:porkchop":10,"spore:biomass":10,"minecraft:rotten_flesh":49,"mysticsbiomes:pink_egg":1,"jeg:rifle_ammo":412,"darkestsouls:titanite_fragment":54,"minecraft:mangrove_door":8,"minecraft:obsidian":48,"minecraft:snowball":22,"minecraft:cobblestone":255,"mysticsbiomes:cherry_door":2,"mysticsbiomes:cherry_planks":43,"minecraft:cooked_beef":402,"minecraft:feather":6,"minecraft:lilac":4,"minecraft:water_bucket":1,"minecraft:flint":4,"darkestsouls:cinnabar":6,"minecraft:tuff":6,"mysticsbiomes:cherry_log":98,"jeg:scrap":122,"minecraft:lapis_lazuli":168,"minecraft:dirt":80,"jeg:combat_rifle":11,"minecraft:glass":1,"minecraft:bone":59,"minecraft:bow":3,"minecraft:wheat_seeds":1,"minecraft:raw_gold":58,"minecraft:glowstone_dust":1,"mysticsbiomes:spring_bamboo":675,"minecraft:oak_planks":127,"darkestsouls:bone_fragment":11,"spore:cerebrum":17,"spore:armor_fragment":77,"spore:claw_fragment":56,"minecraft:diamond":28,"minecraft:golden_apple":2,"minecraft:emerald":10,"darkestsouls:torn_leather_scrap":2,"spore:spine_fragment":13,"minecraft:light_gray_carpet":1,"minecraft:oak_sapling":26,"minecraft:cherry_slab":1,"minecraft:diamond_pickaxe":1,"minecraft:crafting_table":15,"minecraft:chicken":5,"minecraft:brown_mushroom":6,"minecraft:wooden_pickaxe":4,"mysticsbiomes:pink_cherry_blossom_sapling":26,"jeg:scrap_workbench":2,"darkestsouls:kukri":2,"spore:sickle_fragment":5,"minecraft:shield":8,"minecraft:stripped_mangrove_log":4,"minecraft:iron_axe":6,"minecraft:blackstone":13,"spore:armads":3,"minecraft:beef":38,"minecraft:iron_nugget":19,"minecraft:sugar_cane":61,"minecraft:chest":12,"minecraft:birch_sapling":6,"jeg:semi_auto_rifle":1,"minecraft:egg":2,"mysticsbiomes:cherry_stairs":2,"spore:tumor":6,"minecraft:raw_iron":228,"darkestsouls:twinkling_fragment":3,"darkestsouls:soul_fragment":70,"spore:wing_membrane":8,"darkestsouls:torn_cloth_piece":2,"minecraft:copper_ingot":7,"minecraft:bowl":1,"minecraft:carrot":118,"mysticsbiomes:cyan_egg":1,"minecraft:arrow":55,"mysticsbiomes:stripped_cherry_log":1,"minecraft:gold_ingot":2,"spore:alveolic_sack":4,"spore:tendons":32,"minecraft:mutton":7,"minecraft:bone_block":11,"minecraft:white_wool":9,"minecraft:golden_carrot":1,"minecraft:glow_ink_sac":8,"minecraft:salmon":33,"minecraft:leather":16,"minecraft:birch_planks":70,"minecraft:mushroom_stew":1,"minecraft:oak_log":127,"minecraft:golden_boots":2,"darkestsouls:firebomb":3,"minecraft:gunpowder":39,"jeg:grenade":13,"minecraft:birch_pressure_plate":1,"minecraft:apple":3,"darkestsouls:dark_fragment":2,"minecraft:iron_ingot":69,"minecraft:stone_pickaxe":5,"spore:mutated_fiber":319,"darkestsouls:blood_stone_fragment":28,"darkestsouls:rusty_metal_scrap":1,"minecraft:mangrove_planks":760,"minecraft:iron_sword":1,"jeg:tech_trash":23,"minecraft:smooth_basalt":4,"darkestsouls:enchanted_torn_cloth_piece":1,"spore:living_core":2,"darkestsouls:rusty_mail_scrap":1,"minecraft:raw_iron_block":2,"minecraft:gravel":1,"minecraft:amethyst_shard":5,"minecraft:white_bed":4,"minecraft:spruce_door":3,"minecraft:spider_eye":9,"jeg:handmade_shell":1,"spore:fleshy_bone":1,"darkestsouls:siderite_fragment":1,"minecraft:slime_ball":30,"mysticsbiomes:white_cherry_blossom_sapling":12,"minecraft:stone_axe":5,"minecraft:iron_helmet":4,"darkestsouls:small_soul_fragment":22,"minecraft:damaged_anvil":3,"minecraft:coal":415,"darkestsouls:throwing_knife":10,"minecraft:ender_pearl":2},"minecraft:killed_by":{"minecraft:creeper":1,"spore:inf_human":2,"darkestsouls:leech":2,"spore:inf_villager":1,"darkestsouls:skeleton_falchion":1,"minecraft:player":2,"darkestsouls:skeleton_swordsman_twin_shotels":1,"spore:ogre":1,"darkestsouls:ashen_blood_beast_patient":1,"minecraft:skeleton":1,"darkestsouls:church_doctor_pistol":1},"minecraft:custom":{"minecraft:interact_with_crafting_table":82,"minecraft:open_barrel":6,"minecraft:leave_game":12,"minecraft:time_since_death":3543,"minecraft:sprint_one_cm":1189703,"minecraft:damage_blocked_by_shield":4768,"minecraft:drop":72,"minecraft:play_time":366682,"minecraft:deaths":17,"minecraft:jump":4354,"minecraft:interact_with_brewingstand":1,"minecraft:walk_on_water_one_cm":174233,"minecraft:enchant_item":4,"minecraft:interact_with_furnace":39,"minecraft:sleep_in_bed":8,"minecraft:damage_dealt":54899,"minecraft:player_kills":4,"minecraft:crouch_one_cm":57322,"minecraft:interact_with_smoker":8,"minecraft:interact_with_anvil":3,"minecraft:mob_kills":361,"minecraft:damage_dealt_resisted":654,"minecraft:climb_one_cm":776,"minecraft:walk_one_cm":762233,"minecraft:sneak_time":22733,"minecraft:walk_under_water_one_cm":113526,"minecraft:interact_with_blast_furnace":6,"minecraft:total_world_time":366682,"minecraft:time_since_rest":3572,"minecraft:damage_taken":14287,"minecraft:damage_absorbed":454,"minecraft:minecart_one_cm":7014,"minecraft:swim_one_cm":381441,"minecraft:fly_one_cm":1403784,"minecraft:open_chest":224,"minecraft:fall_one_cm":135374},"minecraft:crafted":{"minecraft:oak_planks":508,"minecraft:smooth_stone":5,"minecraft:stone":5,"spore:living_boots":1,"minecraft:iron_boots":2,"spore:fleshy_bone":4,"spore:fleshy_claw":3,"minecraft:chest":19,"minecraft:raw_iron_block":1,"minecraft:smoker":1,"minecraft:wooden_shovel":1,"spore:plated_helmet":1,"minecraft:cooked_porkchop":7,"minecraft:crafting_table":3,"minecraft:iron_helmet":2,"minecraft:wooden_pickaxe":1,"minecraft:raw_gold_block":2,"minecraft:spruce_door":3,"minecraft:copper_ingot":5,"morevanillaarmor:obsidian_boots":1,"spore:spine":1,"spore:armads":1,"minecraft:book":1,"minecraft:iron_chestplate":3,"minecraft:paper":3,"minecraft:shield":3,"minecraft:stick":72,"minecraft:iron_ingot":68,"minecraft:iron_pickaxe":1,"spore:plated_muscle":9,"spore:living_helmet":1,"spore:claw":4,"spore:plated_chest":1,"minecraft:furnace":5,"minecraft:blast_furnace":1,"jeg:scrap_workbench":1,"mysticsbiomes:cherry_planks":388,"minecraft:iron_axe":2,"minecraft:stone_pickaxe":1,"spore:armor_plate":7,"morevanillaarmor:obsidian_helmet":1,"morevanillaarmor:obsidian_leggings":1,"minecraft:cooked_beef":16,"spore:living_core":4,"minecraft:enchanting_table":1,"minecraft:mangrove_door":3,"minecraft:mangrove_planks":336,"minecraft:bucket":1,"mysticsbiomes:cherry_stairs":24,"minecraft:stone_axe":1,"minecraft:air":0,"jeg:scrap_block":1,"spore:living_pants":1,"spore:inf_helmet":1,"minecraft:raw_gold":18,"minecraft:wooden_axe":1,"minecraft:iron_leggings":2,"minecraft:white_bed":1,"spore:nerves":24,"minecraft:torch":220,"spore:scythe":1,"minecraft:lapis_block":9,"morevanillaarmor:obsidian_chestplate":1}},"DataVersion":3465}